[{"name": "DeMoN", "account_id": "332227336", "avatar": "https://steamcdn-a.akamaihd.net/steamcommunity/public/images/avatars/fe/fef49e7fa7e1997310d705b2a6158ff8dc1cdfeb.jpg", "solo_mmr": 3995, "group_mmr": 4390, "mmr_estimate": 4304, "matches_win_history": [-1, -1, 1, -1, 1], "gpm_hisotry": [675, 585, 652, 441, 441], "class": "player", "player_lobby": 5}, {"match_id": 3624242489, "player_slot": 131, "radiant_win": false, "duration": 2301, "game_mode": 22, "lobby_type": 7, "hero_id": 11, "start_time": 1513512413, "version": null, "kills": 7, "deaths": 7, "assists": 16, "skill": null, "xp_per_min": 801, "gold_per_min": 675, "hero_damage": 33780, "tower_damage": 3869, "hero_healing": 803, "last_hits": 333, "lane": null, "lane_role": null, "is_roaming": null, "cluster": 155, "leaver_status": 0, "party_size": null, "win_lose": 1, "period": "last_8hrs", "hero_name": "Shadow Fiend", "hero_img": "http://cdn.dota2.com/apps/dota2/images/heroes/nevermore_sb.png", "class": "hero", "player_lobby": 5}, {"match_id": 3624112255, "player_slot": 0, "radiant_win": false, "duration": 3177, "game_mode": 22, "lobby_type": 7, "hero_id": 11, "start_time": 1513508648, "version": null, "kills": 11, "deaths": 7, "assists": 9, "skill": null, "xp_per_min": 705, "gold_per_min": 585, "hero_damage": 44975, "tower_damage": 2316, "hero_healing": 0, "last_hits": 406, "lane": null, "lane_role": null, "is_roaming": null, "cluster": 154, "leaver_status": 0, "party_size": null, "win_lose": -1, "period": "last_8hrs", "hero_name": "Shadow Fiend", "hero_img": "http://cdn.dota2.com/apps/dota2/images/heroes/nevermore_sb.png", "class": "hero", "player_lobby": 5}, {"match_id": 3623979005, "player_slot": 131, "radiant_win": false, "duration": 3412, "game_mode": 22, "lobby_type": 7, "hero_id": 11, "start_time": 1513504510, "version": null, "kills": 17, "deaths": 13, "assists": 14, "skill": null, "xp_per_min": 742, "gold_per_min": 652, "hero_damage": 51398, "tower_damage": 3865, "hero_healing": 0, "last_hits": 476, "lane": null, "lane_role": null, "is_roaming": null, "cluster": 156, "leaver_status": 0, "party_size": null, "win_lose": 1, "period": "last_8hrs", "hero_name": "Shadow Fiend", "hero_img": "http://cdn.dota2.com/apps/dota2/images/heroes/nevermore_sb.png", "class": "hero", "player_lobby": 5}, {"match_id": 3623898915, "player_slot": 2, "radiant_win": false, "duration": 1935, "game_mode": 22, "lobby_type": 7, "hero_id": 39, "start_time": 1513502010, "version": null, "kills": 7, "deaths": 7, "assists": 9, "skill": null, "xp_per_min": 550, "gold_per_min": 441, "hero_damage": 21013, "tower_damage": 1847, "hero_healing": 0, "last_hits": 171, "lane": null, "lane_role": null, "is_roaming": null, "cluster": 155, "leaver_status": 0, "party_size": null, "win_lose": -1, "period": "last_8hrs", "hero_name": "Queen of Pain", "hero_img": "http://cdn.dota2.com/apps/dota2/images/heroes/queenofpain_sb.png", "class": "hero", "player_lobby": 5}, {"match_id": 3623811392, "player_slot": 4, "radiant_win": false, "duration": 2270, "game_mode": 22, "lobby_type": 7, "hero_id": 57, "start_time": 1513499256, "version": 21, "kills": 9, "deaths": 10, "assists": 10, "skill": null, "xp_per_min": 575, "gold_per_min": 441, "hero_damage": 20384, "tower_damage": 467, "hero_healing": 1859, "last_hits": 156, "lane": 3, "lane_role": 3, "is_roaming": false, "cluster": 155, "leaver_status": 0, "party_size": 1, "win_lose": -1, "period": "last_8hrs", "hero_name": "Omniknight", "hero_img": "http://cdn.dota2.com/apps/dota2/images/heroes/omniknight_sb.png", "class": "hero", "player_lobby": 5}]